loggersdk.py
loggersdk-2.0.dist-info/LICENSE
loggersdk-2.0.dist-info/METADATA
loggersdk-2.0.dist-info/WHEEL
loggersdk-2.0.dist-info/top_level.txt
loggersdk-2.0.dist-info/RECORD
